{"meta_description": "Kiszka  - kwaśne, zsiadłe mleko o zawiesistej konsystencji miękkiej galaretki, o charakterystycznym świeżym i kwaskowatym smaku", "title": "Słownik wyrazów śląskich, gwary śląskiej - - Kiszka", "content": "Na naszej stronie stosowane są pliki cookies i inne technologie służące do zbierania i przetwarzania danych osobowych w sposób zautomatyzowany. Dbamy o Twoją prywatność. Nie zwiększamy zakresu naszych uprawnień. Twoje dane są u nas bezpieczne.", "url": "https://bonclok.pl/slowniczek-wyrazow-slaskich/kiszka.html", "category": "śląskie", "sub_category": "Sery i inne produkty mleczne", "phrase": "Śląska kiszka"}