{"meta_description": "Informacje o Pieremiacze danie tatarskie z wołowiną. Naturalne - 7078547678 w archiwum Allegro. Data zakończenia 2018-03-02 - cena 10 zł", "title": "Pieremiacze danie tatarskie z wołowiną. Naturalne - 7078547678 - oficjalne archiwum Allegro", "content": "-Wszystkie zdjęcia naszych produktów są naszego autorstwa i są naszą własnością, zabrania się kopiowania bez naszej wiedzy. -Paczki wysyłamy do środy włącznie (Poniedziałek,wtorek,środa) ze względu aby jedzenie nie zalegało u kuriera w magazynie ale też czasem nie mamy wpływu na kurierów i ich pracę. -Kupujesz przykładowo 4x250gram nie zawsze się wiąże z tym że dostaniecie 4 szynki po równo 250gram, dostaniecie kilogram ale na przykład w trzech szynkach lub dwóch chyba ale waga kilograma będzie się zgadzać (może być troszkę mniej lub troszkę więcej) -Staramy się nie ciąć wyrobów ale jeżeli brakuje do konkretnej wagi może być zapakowany ucięty kawałek -Pamiętaj że przed kupnem warto się zapytać jeżeli są jakieś wątpliwości chętnie udzielę informacji", "url": "https://archiwum.allegro.pl/oferta/pieremiacze-danie-tatarskie-z-wolowina-naturalne-i7078547678.html", "category": "lubelskie", "sub_category": "Gotowe dania i potrawy", "phrase": "Pieremiacze"}