{"meta_description": "Certyfikat dla \"Boczku z Wetliny\" - Willa Łuka, Tulin i Watra - | w Wetlinie", "title": "Certyfikat dla \"Boczku z Wetliny\" -", "content": "Kolejny produkt Bieszczadzkiej Wędzarni \"ŁUKA\" uzyskał jako pierwszy w Bieszczadach jeden z najbardziej cenionych przez konsumentów certyfikatów jakości. Od 9 października 2013 roku \"Boczek z Wetliny\" znajduje sie na liście produktów tradycyjnych województwa podkarpackiego.  Szczegółowe informacje dotyczące naszego produktu znajdziecie Państwo na stronie Ministerstwa Rolnictwa pod podanym niżej linkiem: Boczek z Wetliny", "url": "https://willaluka.pl/certyfikat-dla-boczku-z-wetliny/", "category": "podkarpackie", "sub_category": "Mięso świeże oraz produkty mięsne", "phrase": "Boczek z Wetliny"}