{"meta_description": "Królewskie Miody to sprawdzona pasieka zajmująca się produkcją miodu, jego rozlewem i sprzedażą. Spróbuj miodu z Podkarpacia - zamów ze sklepu online!", "title": "Natura z Podkarpacia", "content": "Królewskie miody to pasieka oferująca miody z podkarpacia i produkty pszczele Królewskie Miody to najnowsze gospodarstwo pszczelarskie oraz sklep z miodem o różnorodnej ofercie i produktów pszczelich z pięknego Podkarpacia. Sprawdzona pasieka to MY! Bezpieczeństwo produkcji jest kontrolowane na każdym etapie. Etap zbioru miodu od kwiatów do słoika kontroluje weterynaria natomiast od momentu załączenie etykiety na słoik przejmuje WIHARS i SANEPID. Profesjonalna i szybka obsługa oraz najwyższe standardy jakości to nasze atuty. Prowadzimy sprzedaż wysyłkową miodu pasiecznego od 2008 r dlatego dbamy o każdy szczegół związany z wysyłką. Zapraszamy do rozkoszowania się ich smakiem i aromatem, a także doświadczenia ich właściwości zdrowotnych znanych od wieków.", "url": "https://krolewskie-miody.pl/", "category": "świętokrzyskie", "sub_category": "Miody", "phrase": "Miód królewski z Osieka"}