{"meta_description": "Składniki   cukier  suszony koncentrat soku buraka czerwonego (17,6 %)  sól  regulator kwasowości: kwas cytrynowy  warzywa suszone: czosnek, cebula  wzmacniacze smaku: glutaminian monos", "title": "Zupa błyskawiczna barszcz czerwony instant 28 g Kucharek - Hurt market", "content": "Tysiące przepisów znajdziesz na: Doradcasmaku.pl Loteria 1. W terminie 15.10.2021 - 17.04.2022 kup dowolny produkt marki Kucharek (nie musi być oznaczony informacją o loterii) i zachowaj paragon. 2. Wejdź na stronę loteria.kucharek.pl i weź udział w loterii. Do wygrania: nagroda główna: rodzinne auto codziennie* 500 zł *Codziennie w okresie sprzedaży promocyjnej i przyjmowania zgłoszeń do loterii tj.: 15.10.2021 - 17.04.2022 r. Szczegóły i regulamin na: loteria.kucharek.pl. Organizator: First Line Polska sp. z o.o. z siedzibą w Warszawie.", "url": "https://szybkihurt.pl/zupa-blyskawiczna-barszcz-czerwony-instant-28-g-kucharek.html", "category": "lubelskie", "sub_category": "Gotowe dania i potrawy", "phrase": "Barszcz czereśniowy"}