{"meta_description": "Zobacz najnowsze dokładne i aktualne Browar Restauracja Grodzka 15 Ceny w Menu (PL) dla całego menu, w tym najpopularniejszych pozycji w menu. (Poland)", "title": "Browar Restauracja Grodzka 15 Ceny w Menu (PL)", "content": "PriceListo gromadzi aktualne informacje o cenach ze źródeł, takich jak wizyty na miejscu, witryny firmowe i wywiady telefoniczne. Ceny podane na tej stronie pochodzą z co najmniej jednego z tych źródeł. Oczywiście ceny podane na tej stronie mogą nie być aktualne i mogą nie mieć zastosowania do wszystkich lokalizacji danej marki biznesowej. Aby uzyskać aktualne ceny, skontaktuj się z indywidualną lokalizacją firmy, która Cię interesuje.", "url": "https://www.pricelisto.com/menu-prices/browar-restauracja-grodzka-15-pl", "category": "lubelskie", "sub_category": "Orzechy, nasiona, zboża, warzywa i owoce (przetworzone i nie)", "phrase": "Krężałki księżpolskie"}