{"meta_description": "", "title": "DS 21: Wielkanocne jedzenie dla dzieci", "content": " • None zające czekoladowe Favorina, Lidl, zając z mlecznej czekolady, Favorina, Lidl, zając z białej czekolady, Favorina, Lidl, Figurka z czekolady mlecznej, Heidi Zając Z Kokardą Mleczna Figurka, Terravita – Zając z mlecznej czekolady, Lindt Edycja limitowana Mini zajączki z mlecznej czekolady, Merci Zając Czekolada mleczna, Milka Zając z czekolady mlecznej z mleka alpejskiego, Lindt Edycja limitowana Zajączek z mlecznej czekolady, Lindt Zajączek i marchewki z mlecznej czekolady • None kiełbasy Tesco Finest Kiełbasa swojska pilzneńska, Taurus Kiełbasa wiejska, Madej Wróbel Simply food… so good Kiełbasa śląska, Tesco Finest Kiełbasa swojska drobiowo-wieprzowa pilzneńska, SOKOŁÓW Naturrino Kiełbasa z piersi kurczaka, SOKOŁÓW Kiełbasa myśliwska, TRADYCYJNE JADŁO Kiełbasa z orzechami laskowymi podwędzana dojrzewająca, Konspol – Kiełbasa wiejska wieprzowa bez glutenu, bez laktozy • None parówki Madej Wróbel Simply food… so good Parówki z szynki, Drobimex NaturMisie Paróweczki z kurcząt, GOODVALLEY Parówki z szynki dla dzieci bezglutenowe, GOODVALLEY Kiełbaski z szynki dla dzieci bezglutenowe, Konspol Znakomite Parówki Z Piersi Kurczaka, Pikok Lidl Parówki z szynki, Piratki (Lidl), Kraina Wędlin Nature (Biedronka), Kraina Wędlin, Głodniaki, parówki z szynki i cielęciny, Pikok Pure (Lidl), Parówki z indyka,", "url": "https://dietetykasmyka.pl/ds-21-wielkanocne-jedzenie-dla-dzieci/", "category": "podkarpackie", "sub_category": "Mięso świeże oraz produkty mięsne", "phrase": "Kiełbasa swojska drobiowo-wieprzowa pilzneńska"}