{"meta_description": "", "title": "Produkty – VitaCORN", "content": "VITACORN jest producentem olei, które swoimi walorami zasłużyły na uznanie i zostały wpisane na Listę Produktów Tradycyjnych Ministerstwa Rolnictwa i Rozwoju Wsi oraz posiadają certyfikat JAKOŚĆ TRADYCJA. Należy do nich OLEJ Z PESTEK DYNI oraz OLEJ RZEPAKOWY “WIELKOPOLSKI”. Produkowane przez firmę oleje powstają na bazie surowca starannie dobranego pod względem jakości, dostarczanego od lat przez stałych, współpracujących z firmą producentów rolnych. Ponadto VITACORN produkuje również olej sezamowy, słonecznikowy, z orzechów włoskich, olej lniany ” złocisty” i inne. Drugim nurtem produkcji są wyroby z grupy tzw. “zdrowej żywności”, to znaczny takie, które (poza typową dla produktów zbożowych wartością odżywczą) posiadają niezaprzeczalne profilaktyczne i zdrowotne walory – na przykład bogate w błonnik, obniżające cholesterol, a także wspomagające procesy metaboliczne. Są to między innymi: siemię lniane, pestki dyni, otręby owsiane, otręby pszenne, otręby żytnie z dodatkiem suszonych owoców, kaszki kukurydziane, kaszki jaglane, mąka kukurydziana, mąka owsiana. Informujemy, że od dnia 1 lutego 2022 r. do 31 lipca 2022 r. ceny naszych produktów objęte są stawką podatku od towarów i usług obniżoną do wysokości 0%.", "url": "https://www.vitacorn.com.pl/sklep/", "category": "wielkopolskie", "sub_category": "Oleje i tłuszcze (masło, margaryna itp.)", "phrase": "Olej z pestek dyni wielkopolski"}