{"meta_description": "Sprawdź NIP i REGON firmy Patryk Samelak. Przeczytaj opinie jej klientów. Dowiedz się jakie są powiązania pomiędzy firmami. Dane z rejestru CEIDG.", "title": "Firma Patryk Samelak, Poznań - NIP, REGON, opinie, dotacje unijne - Dane z CEIDG - Sklepy internetowe", "content": "Czy to Twoja firma? Zdobywaj nowych klientów i otrzymuj powiadomienia o nowych opiniach. Zarejestruj się i bezpłatnie korzystaj z funkcji serwisu!", "url": "https://aleo.com/pl/firma/patryk-samelak", "category": "śląskie", "sub_category": "Produkty rybołówstwa, w tym ryby", "phrase": "Karp gołyski"}