{"meta_description": "Dzik duszony z grzybami fantastyczne danie, bardzo aromatyczne i delikatne mięso. Koniecznie sprawdź przepis!", "title": "Dzik duszony z grzybami Chefa", "content": "Dzik duszony z grzybami Chefa to fantastyczne danie pełne smaku i aromatów. Mięso dzika i grzyby to z pewnością idealne połączenie. Dzięki składnikom powstaje przepyszny sos, który z przyjemnością wyjesz ze świeżą bagietką. Jeśli tylko będziesz mieć okazję kupić dziczyznę koniecznie wypróbuj ten przepis. Mięso dokładnie umyj, następnie osącz z wody. Włóż do emaliowanego lub np. szklanego naczynia, zalej marynatą i odstaw do lodówki na trzy dni. Mięso przewracaj w marynacie dwa razy dziennie. Mięso wyjmij z lodówki przynajmniej na 1 godzinę przed pieczeniem, następnie osącz i pokrój na kawałki. Cebulę pokrój w półtalarki. Większe grzyby pokrój na kawałki. Na patelni silnie rozgrzej połowę masła i oleju i obsmaż mięso ze wszystkich stron. Na pozostałym na patelni tłuszczu podsmaż na złoty kolor cebulkę, następnie dodaj bulion.   Do brytwanny włóż resztę masła i oleju, przełóż podsmażone mięso, dodaj grzyby i zalej połową bulionu z cebulką. Duś mięso z grzybami na małym ogniu, aż będzie całkowicie miękkie, (około 2 godziny) podlewaj pozostałym bulionem (i ewentualnie wodą od grzybów). Śmietanę zahartuj sosem i powoli dodaj do mięsa.   Podawaj z podpiekaną kaszą gryczną, kiszonym ogórkiem i konserwową papryką. Jeśli chcesz być na bieżąco z moimi przepisami to zapraszam na Facebook i Instagram.", "url": "https://kuron.com.pl/artykuly/przepisy/dania-glowne/dzik-duszony-z-grzybami/", "category": "lubelskie", "sub_category": "Mięso świeże oraz produkty mięsne", "phrase": "Dzik w cieście"}