{"meta_description": "Gzik wielkopolski 200g chez Intermarché. Drive et livraison à domicile. Vos courses en ligne au même prix que dans votre magasin.", "title": "Gzik wielkopolski 200g OSM TOP-TOMYŚL – Intermarché", "content": "Opis produktu: Gzik wielkopolski to tradycyjny produkt, wytwarzany z rozdrobnionego twarogu, który następnie miesza się z dodatkiem śmietany, soli i pieprzu na jednolitą masę. Tak przyrządzony gzik podawany był (i jest nadal) jako dodatek do ziemniaków w mundurkach, a obecnie jest pysznym dodatkiem do kanapek.", "url": "https://drive.intermarche.pl/drive-catalogue/produit/43571-osm-top-tomysl-gzik-wielkopolski-200g", "category": "wielkopolskie", "sub_category": "Sery i inne produkty mleczne", "phrase": "Gzik wielkopolski"}