{"meta_description": "Pierogi po kaszubsku 400 g chez Intermarché. Drive et livraison à domicile. Vos courses en ligne au même prix que dans votre magasin.", "title": "Pierogi po kaszubsku 400 g Proste Historie – Intermarché", "content": " • Gotowy do spożycia po obróbce cieplnej. Instrukcje dotyczące przygotowania:  Gotować we wrzątku - Od postaci zamrożonej   1. Zamrożone pierogi wyjmij z opakowania i wrzuć do około 3 litrów wrzącej, osolonej wody. 2. Następnie pierogi delikatnie przemieszaj, aby nie przylegały do dna. Gotuj na wolnym ogniu 10-12 minut. 3. Ugotowane pierogi wyjmij z wody i podaj je tak jak lubisz. Możesz polać sosem lub tłuszczem z dodatkiem smażonej cebuli. • Opis produktu: Kaszuby słyną nie tylko z pięknych krajobrazów, ale także z wyśmienitej kuchni. Zainspirowani regionalnymi smakami, proponujemy... pierogi z kaszanką. Brzmi ciekawie? Pewnie, że tak, ale najważniejsze, że to danie jest po prostu smaczne.   Cechy: kaszubskie smaki z kaszanką z Kaszub  bez konserwantów z kaszą jęczmienną • Warunki przechowywania:- w temperaturze -6°C: 1 tydzień- w temperaturze -12°C: 1 miesiąc- w temperaturze poniżej -18°C: do końca daty minimalnej trwałości podanej na opakowaniu.Chronić przed rozmrożeniem. Wyrób rozmrożony nie kwalifikuje się do powtórnego zamrożenia. • Naszym celem jest dostarczenie jak najbardziej wiarygodnych informacji o sprzedawanych produktach. By mieć pewność, że skład oraz wartości odżywcze i alergeny nie uległy zmianie, zalecamy sprawdzić etykietę produktową przed spożyciem produktu.", "url": "https://drive.intermarche.pl/drive-catalogue/produit/55728-proste-historie-pierogi-po-kaszubsku-400-g", "category": "pomorskie", "sub_category": "Mięso świeże oraz produkty mięsne", "phrase": "Kaszanka po kaszubsku "}